{
  "-JWeo0s3h9c7q3v3fb-J": {
    "firebaseKey":"-JWeo0s3h9c7q3v3fb-J",
    "student_id": "-ZwDujOVia-HaPGPHb-N",
    "quizzes":99.5,
    "homework":85.0,
    "classwork":62.2,
    "projects":81.2,
    "exams":81.1,
    "isPassing":true
  },
  "-FZia0m5q4l2c0r7oq-N": {
    "firebaseKey":"-FZia0m5q4l2c0r7oq-N",
    "student_id": "-XaDfpPXya-CtMENVj-Q",
    "quizzes":80.3,
    "homework":68.2,
    "classwork":65.1,
    "projects":81.4,
    "exams":83.1,
    "isPassing":true
  },
  "-GWkj6f9v5s0p0j3ty-D": {
    "firebaseKey":"-GWkj6f9v5s0p0j3ty-D",
    "student_id": "-WkSwxVQwl-LlHSIEl-K",
    "quizzes":88.3,
    "homework":61.5,
    "classwork":93.0,
    "projects":60.3,
    "exams":77.5,
    "isPassing":true
  }
}
